ecxclient/__init__.py
ecxclient/cli/__init__.py
ecxclient/cli/ecxcli.py
ecxclient/cli/util.py
ecxclient/cli/commands/__init__.py
ecxclient/cli/commands/cmd_job.py
ecxclient/cli/commands/cmd_logs.py
ecxclient/cli/commands/cmd_resource.py
ecxclient/sdk/__init__.py
ecxclient/sdk/client.py
ecxclient-0.42.dist-info/DESCRIPTION.rst
ecxclient-0.42.dist-info/METADATA
ecxclient-0.42.dist-info/RECORD
ecxclient-0.42.dist-info/WHEEL
ecxclient-0.42.dist-info/entry_points.txt
ecxclient-0.42.dist-info/metadata.json
ecxclient-0.42.dist-info/top_level.txt
