Metadata-Version: 2.0
Name: ecxclient
Version: 0.42
Summary: A client for Catalogic Software's ECX. 
Home-page: https://github.com/catalogicsoftware/ecxclient
Author: Catalogic Software
Author-email: raghu@catalogicsoftware.com
License: Apache License 2.0
Keywords: development
Platform: UNKNOWN
Classifier: Development Status :: 4 - Beta
Classifier: Intended Audience :: Developers
Classifier: Topic :: Software Development
Classifier: License :: OSI Approved :: Apache Software License
Classifier: Programming Language :: Python :: 2
Classifier: Programming Language :: Python :: 2.6
Requires-Dist: click
Requires-Dist: requests
Requires-Dist: tabulate
Provides-Extra: dev
Requires-Dist: check-manifest; extra == 'dev'
Provides-Extra: test
Requires-Dist: coverage; extra == 'test'
